tlgbot/__init__.py
tlgbot/rest.py
tlgbot/tlgbot.py
tlgbot-1.3.dist-info/METADATA
tlgbot-1.3.dist-info/WHEEL
tlgbot-1.3.dist-info/top_level.txt
tlgbot-1.3.dist-info/RECORD
