Metadata-Version: 2.1
Name: tlgbot
Version: 1.3
Summary: TLGBot is a Python library for creating Telegram bots with ease. This library simplifies the interaction with the Telegram Bot API, allowing you to send messages, edit group descriptions, and more.
Home-page: UNKNOWN
Author: GDLegions
Author-email: usaboy2133@tuta.io
License: UNKNOWN
Project-URL: Documentation, https://github.com/GDLegions/tlgbot/blob/main/README.md
Project-URL: GitHub Repository, https://github.com/GDLegions/tlgbot
Platform: UNKNOWN
Classifier: Development Status :: 5 - Production/Stable
Classifier: Intended Audience :: Developers
Classifier: License :: OSI Approved :: MIT License
Classifier: Programming Language :: Python :: 3
Classifier: Programming Language :: Python :: 3.6
Classifier: Programming Language :: Python :: 3.7
Classifier: Programming Language :: Python :: 3.8
Classifier: Programming Language :: Python :: 3.9
Classifier: Topic :: Software Development :: Libraries
Classifier: Topic :: Software Development :: Libraries :: Python Modules
Requires-Dist: requests
